nd_prover/__init__.py
nd_prover/__main__.py
nd_prover/cli.py
nd_prover/logic.py
nd_prover/parser.py
nd_prover/prover.py
nd_prover/tfl_sat.py
nd_prover-2.0.0.dist-info/licenses/LICENSE
nd_prover-2.0.0.dist-info/METADATA
nd_prover-2.0.0.dist-info/WHEEL
nd_prover-2.0.0.dist-info/entry_points.txt
nd_prover-2.0.0.dist-info/top_level.txt
nd_prover-2.0.0.dist-info/RECORD
