Metadata-Version: 2.4
Name: nd-prover
Version: 2.0.0
Summary: Natural deduction proof generator & checker
Author-email: Daniyal Akif <daniyalakif@gmail.com>
License: MIT
Project-URL: Homepage, https://ndprover.org
Project-URL: Repository, https://github.com/daniyal1249/nd-prover
Keywords: python,math,logic,proof checker,natural deduction,fitch,fitch proofs,modal logic
Classifier: Development Status :: 5 - Production/Stable
Classifier: Intended Audience :: Science/Research
Classifier: License :: OSI Approved :: MIT License
Classifier: Programming Language :: Python :: 3
Classifier: Programming Language :: Python :: 3.10
Classifier: Programming Language :: Python :: 3.11
Classifier: Programming Language :: Python :: 3.12
Classifier: Programming Language :: Python :: 3.13
Classifier: Topic :: Scientific/Engineering :: Mathematics
Classifier: Operating System :: OS Independent
Requires-Python: >=3.10
License-File: LICENSE
Dynamic: license-file
